biopython/__init__.py
biopython_custom-0.1.dist-info/METADATA
biopython_custom-0.1.dist-info/WHEEL
biopython_custom-0.1.dist-info/top_level.txt
biopython_custom-0.1.dist-info/RECORD
