Metadata-Version: 2.4
Name: biopython-custom
Version: 0.1
Summary: Custom tools for bioinformatics
Author: Your Name
Classifier: Programming Language :: Python :: 3
Classifier: License :: OSI Approved :: MIT License
Dynamic: author
Dynamic: classifier
Dynamic: description
Dynamic: description-content-type
Dynamic: summary
